colorprints/__init__.py
colorprints/main.py
colorprints-1.43.dist-info/METADATA
colorprints-1.43.dist-info/WHEEL
colorprints-1.43.dist-info/top_level.txt
colorprints-1.43.dist-info/RECORD
