Metadata-Version: 2.1
Name: colorprints
Version: 1.43
Summary: Simple Color Prints library made as classwork
